pylogconf/__init__.py
pylogconf/core.py
pylogconf/static.py
pylogconf-0.0.38.dist-info/LICENSE
pylogconf-0.0.38.dist-info/METADATA
pylogconf-0.0.38.dist-info/WHEEL
pylogconf-0.0.38.dist-info/top_level.txt
pylogconf-0.0.38.dist-info/RECORD
