Metadata-Version: 2.1
Name: pylogconf
Version: 0.0.38
Summary: correctly configure python logging
Home-page: https://veltzer.github.io/pylogconf
Download-URL: https://github.com/veltzer/pylogconf
Author: Mark Veltzer
Author-email: mark.veltzer@gmail.com
Maintainer: Mark Veltzer
Maintainer-email: mark.veltzer@gmail.com
License: MIT
Keywords: python,logging,configuration,easy,yaml,json,debug
Platform: python3
Classifier: Development Status :: 4 - Beta
Classifier: Environment :: Console
Classifier: Operating System :: OS Independent
Classifier: Programming Language :: Python
Classifier: Programming Language :: Python :: 3
Classifier: Programming Language :: Python :: 3 :: Only
Classifier: Programming Language :: Python :: 3.11
Classifier: Topic :: Utilities
Classifier: License :: OSI Approved :: MIT License
License-File: LICENSE
Requires-Dist: pyfakeuse
Requires-Dist: logging-tree
Requires-Dist: pyyaml
